jupyterlab_ai_assistant/__init__.py
jupyterlab_ai_assistant/_post_install.py
jupyterlab_ai_assistant/_version.py
jupyterlab_ai_assistant/config.py
jupyterlab_ai_assistant/handlers.py
jupyterlab_ai_assistant/ollama_client.py
jupyterlab_ai_assistant-1.1.1.data/data/etc/jupyter/jupyter_notebook_config.d/jupyterlab_ai_assistant.json
jupyterlab_ai_assistant-1.1.1.data/data/etc/jupyter/jupyter_server_config.d/jupyterlab_ai_assistant.json
jupyterlab_ai_assistant-1.1.1.data/data/share/jupyter/labextensions/jupyterlab-ai-assistant/package.json
jupyterlab_ai_assistant-1.1.1.data/data/share/jupyter/labextensions/jupyterlab-ai-assistant/schemas/jupyterlab-ai-assistant/package.json.orig
jupyterlab_ai_assistant-1.1.1.data/data/share/jupyter/labextensions/jupyterlab-ai-assistant/schemas/jupyterlab-ai-assistant/plugin.json
jupyterlab_ai_assistant-1.1.1.data/data/share/jupyter/labextensions/jupyterlab-ai-assistant/static/354.7505e99a92834cbd431a.js
jupyterlab_ai_assistant-1.1.1.data/data/share/jupyter/labextensions/jupyterlab-ai-assistant/static/354.7505e99a92834cbd431a.js.LICENSE.txt
jupyterlab_ai_assistant-1.1.1.data/data/share/jupyter/labextensions/jupyterlab-ai-assistant/static/378.f92ee8ece7d2d240efe0.js
jupyterlab_ai_assistant-1.1.1.data/data/share/jupyter/labextensions/jupyterlab-ai-assistant/static/570.273f804d1bc3c18d0938.js
jupyterlab_ai_assistant-1.1.1.data/data/share/jupyter/labextensions/jupyterlab-ai-assistant/static/665.71d5a82fbcb15cb77660.js
jupyterlab_ai_assistant-1.1.1.data/data/share/jupyter/labextensions/jupyterlab-ai-assistant/static/remoteEntry.6047eac7bcd7ebeefb8c.js
jupyterlab_ai_assistant-1.1.1.data/data/share/jupyter/labextensions/jupyterlab-ai-assistant/static/style.js
jupyterlab_ai_assistant-1.1.1.data/data/share/jupyter/labextensions/jupyterlab-ai-assistant/static/third-party-licenses.json
jupyterlab_ai_assistant-1.1.1.dist-info/METADATA
jupyterlab_ai_assistant-1.1.1.dist-info/WHEEL
jupyterlab_ai_assistant-1.1.1.dist-info/licenses/LICENSE
jupyterlab_ai_assistant-1.1.1.dist-info/RECORD
