Metadata-Version: 2.4
Name: jupyterlab_ai_assistant
Version: 1.1.1
Summary: A JupyterLab extension that integrates Ollama-powered AI assistance directly into notebooks
Project-URL: Homepage, https://github.com/bhumukul-raj/ollama-ai-assistant-project
Project-URL: Bug Tracker, https://github.com/bhumukul-raj/ollama-ai-assistant-project/issues
Project-URL: Repository, https://github.com/bhumukul-raj/ollama-ai-assistant-project.git
Author-email: bhumukulraj <bhumukulraj@gmail.com>
License-File: LICENSE
Keywords: ai,jupyter,jupyterlab,jupyterlab-extension,ollama
Classifier: Framework :: Jupyter
Classifier: Framework :: Jupyter :: JupyterLab
Classifier: Framework :: Jupyter :: JupyterLab :: 4
Classifier: Framework :: Jupyter :: JupyterLab :: Extensions
Classifier: Framework :: Jupyter :: JupyterLab :: Extensions :: Prebuilt
Classifier: License :: OSI Approved :: MIT License
Classifier: Programming Language :: Python
Classifier: Programming Language :: Python :: 3
Classifier: Programming Language :: Python :: 3.8
Classifier: Programming Language :: Python :: 3.9
Classifier: Programming Language :: Python :: 3.10
Classifier: Programming Language :: Python :: 3.11
Requires-Python: >=3.8
Requires-Dist: aiohttp
Requires-Dist: jupyter-server>=2.0.0
Requires-Dist: jupyterlab<5.0.0,>=4.0.0
Requires-Dist: requests>=2.25.0
Provides-Extra: dev
Requires-Dist: black==23.3.0; extra == 'dev'
Requires-Dist: jupyter-server<3.0.0,>=2.0.0; extra == 'dev'
Requires-Dist: pytest; extra == 'dev'
Requires-Dist: pytest-cov; extra == 'dev'
Requires-Dist: pytest-jupyter>=0.5.3; extra == 'dev'
